{
  "gitSyncId": "65239c609e2c5d386003eff6_65289e44267b0f20e5609002",
  "id": "Login Page_auth.formatTime",
  "pluginId": "js-plugin",
  "pluginType": "JS",
  "unpublishedAction": {
    "actionConfiguration": {
      "encodeParamsToggle": true,
      "jsArguments": [
        {
          "name": "timestamp"
        }
      ],
      "paginationType": "NONE",
      "timeoutInMillisecond": 10000
    },
    "collectionId": "Login Page_auth",
    "confirmBeforeExecute": false,
    "datasource": {
      "isAutoGenerated": false,
      "name": "UNUSED_DATASOURCE",
      "pluginId": "js-plugin"
    },
    "dynamicBindingPathList": [
      {
        "key": "body"
      }
    ],
    "executeOnLoad": false,
    "fullyQualifiedName": "auth.formatTime",
    "name": "formatTime",
    "pageId": "Login Page",
    "userSetOnLoad": false
  }
}