{
  "gitSyncId": "65239c609e2c5d386003eff6_652e542e4f6e207987bd50c7",
  "id": "Settings_app.removeCountryCode",
  "pluginId": "js-plugin",
  "pluginType": "JS",
  "unpublishedAction": {
    "actionConfiguration": {
      "encodeParamsToggle": true,
      "jsArguments": [
        {
          "name": "contact"
        },
        {
          "name": "country"
        }
      ],
      "paginationType": "NONE",
      "timeoutInMillisecond": 10000
    },
    "collectionId": "Settings_app",
    "confirmBeforeExecute": false,
    "datasource": {
      "isAutoGenerated": false,
      "name": "UNUSED_DATASOURCE",
      "pluginId": "js-plugin"
    },
    "dynamicBindingPathList": [
      {
        "key": "body"
      }
    ],
    "executeOnLoad": false,
    "fullyQualifiedName": "app.removeCountryCode",
    "name": "removeCountryCode",
    "pageId": "Settings",
    "userSetOnLoad": false
  }
}