{
  "accentColor": "{{appsmith.theme.colors.primaryColor}}",
  "allowAddNewRow": false,
  "animateLoading": true,
  "borderColor": "#E0DEDE",
  "borderRadius": "{{appsmith.theme.borderRadius.appBorderRadius}}",
  "borderWidth": "1",
  "bottomRow": 32,
  "boxShadow": "{{appsmith.theme.boxShadow.appBoxShadow}}",
  "canFreezeColumn": true,
  "childStylesheet": {
    "button": {
      "borderRadius": "{{appsmith.theme.borderRadius.appBorderRadius}}",
      "boxShadow": "none",
      "buttonColor": "{{appsmith.theme.colors.primaryColor}}"
    },
    "editActions": {
      "discardBorderRadius": "{{appsmith.theme.borderRadius.appBorderRadius}}",
      "discardButtonColor": "{{appsmith.theme.colors.primaryColor}}",
      "saveBorderRadius": "{{appsmith.theme.borderRadius.appBorderRadius}}",
      "saveButtonColor": "{{appsmith.theme.colors.primaryColor}}"
    },
    "iconButton": {
      "borderRadius": "{{appsmith.theme.borderRadius.appBorderRadius}}",
      "boxShadow": "none",
      "buttonColor": "{{appsmith.theme.colors.primaryColor}}"
    },
    "menuButton": {
      "borderRadius": "{{appsmith.theme.borderRadius.appBorderRadius}}",
      "boxShadow": "none",
      "menuColor": "{{appsmith.theme.colors.primaryColor}}"
    }
  },
  "columnOrder": [
    "id",
    "source",
    "unit_energy",
    "co2_energy",
    "gwp",
    "ch4_energy",
    "n2o_energy",
    "co2e_energy",
    "unit_mass",
    "co2_mass",
    "ch4_mass",
    "n2o_mass",
    "co2e_mass",
    "year",
    "reference",
    "created_by",
    "role",
    "notes"
  ],
  "columnUpdatedAt": 1709280855798,
  "columnWidthMap": {},
  "defaultPageSize": 0,
  "defaultSelectedRowIndex": 0,
  "defaultSelectedRowIndices": [
    0
  ],
  "delimiter": ",",
  "displayName": "Table",
  "dynamicBindingPathList": [
    {
      "key": "accentColor"
    },
    {
      "key": "borderRadius"
    },
    {
      "key": "boxShadow"
    },
    {
      "key": "primaryColumns.id.computedValue"
    },
    {
      "key": "primaryColumns.source.computedValue"
    },
    {
      "key": "primaryColumns.notes.computedValue"
    },
    {
      "key": "primaryColumns.year.computedValue"
    },
    {
      "key": "primaryColumns.created_by.computedValue"
    },
    {
      "key": "primaryColumns.reference.computedValue"
    },
    {
      "key": "primaryColumns.role.computedValue"
    },
    {
      "key": "primaryColumns.gwp.computedValue"
    },
    {
      "key": "tableData"
    },
    {
      "key": "primaryColumns.unit_energy.computedValue"
    },
    {
      "key": "primaryColumns.co2_energy.computedValue"
    },
    {
      "key": "primaryColumns.ch4_energy.computedValue"
    },
    {
      "key": "primaryColumns.n2o_energy.computedValue"
    },
    {
      "key": "primaryColumns.co2e_energy.computedValue"
    },
    {
      "key": "primaryColumns.unit_mass.computedValue"
    },
    {
      "key": "primaryColumns.co2_mass.computedValue"
    },
    {
      "key": "primaryColumns.ch4_mass.computedValue"
    },
    {
      "key": "primaryColumns.n2o_mass.computedValue"
    },
    {
      "key": "primaryColumns.co2e_mass.computedValue"
    }
  ],
  "dynamicPropertyPathList": [],
  "dynamicTriggerPathList": [
    {
      "key": "onPageChange"
    },
    {
      "key": "onSort"
    },
    {
      "key": "onAddNewRowSave"
    }
  ],
  "enableClientSideSearch": false,
  "enableServerSideFiltering": false,
  "hideCard": false,
  "horizontalAlignment": "LEFT",
  "iconSVG": "/static/media/icon.e6911f8bb94dc6c4a102a74740c41763.svg",
  "inlineEditingSaveOption": "ROW_LEVEL",
  "isDeprecated": false,
  "isLoading": false,
  "isSortable": true,
  "isVisible": true,
  "isVisibleDownload": false,
  "isVisibleFilters": true,
  "isVisiblePagination": true,
  "isVisibleSearch": true,
  "key": "57chpjy6io",
  "label": "Data",
  "leftColumn": 0,
  "minWidth": 450,
  "mobileBottomRow": 28,
  "mobileLeftColumn": 0,
  "mobileRightColumn": 34,
  "mobileTopRow": 0,
  "needsHeightForContent": true,
  "onAddNewRowSave": "{{Insert_cms_s1_factors2.run(() => {\n            showAlert(\"Successfully created!\");\n            Select_cms_s1_factors2.run()\n          }, () => {\n            showAlert(\"Unable to create!\");\n          })}}",
  "onPageChange": "{{\n            Select_cms_s1_factors2.run();\n            Total_record_cms_s1_factors3.run()\n          }}",
  "onSort": "{{\n            Select_cms_s1_factors2.run();\n            Total_record_cms_s1_factors3.run()\n          }}",
  "parentColumnSpace": 13.46875,
  "parentId": "m61bh8z825",
  "parentRowSpace": 10,
  "primaryColumnId": "id",
  "primaryColumns": {
    "ch4_energy": {
      "alias": "ch4_energy",
      "allowCellWrapping": false,
      "allowSameOptionsInNewRow": true,
      "cellBackground": "",
      "columnType": "number",
      "computedValue": "{{Table1.processedTableData.map((currentRow, currentIndex) => ( currentRow[\"ch4_energy\"]))}}",
      "currencyCode": "USD",
      "decimals": 0,
      "enableFilter": true,
      "enableSort": true,
      "fontStyle": "",
      "horizontalAlignment": "LEFT",
      "id": "ch4_energy",
      "index": 4,
      "isCellEditable": false,
      "isCellVisible": true,
      "isDerived": false,
      "isDisabled": false,
      "isDiscardVisible": true,
      "isEditable": false,
      "isSaveVisible": true,
      "isVisible": true,
      "label": "ch4_energy",
      "notation": "standard",
      "originalId": "ch4_energy",
      "sticky": "",
      "textColor": "",
      "textSize": "0.875rem",
      "thousandSeparator": true,
      "validation": {},
      "verticalAlignment": "CENTER",
      "width": 150
    },
    "ch4_mass": {
      "alias": "ch4_mass",
      "allowCellWrapping": false,
      "allowSameOptionsInNewRow": true,
      "cellBackground": "",
      "columnType": "number",
      "computedValue": "{{Table1.processedTableData.map((currentRow, currentIndex) => ( currentRow[\"ch4_mass\"]))}}",
      "currencyCode": "USD",
      "decimals": 0,
      "enableFilter": true,
      "enableSort": true,
      "fontStyle": "",
      "horizontalAlignment": "LEFT",
      "id": "ch4_mass",
      "index": 9,
      "isCellEditable": false,
      "isCellVisible": true,
      "isDerived": false,
      "isDisabled": false,
      "isDiscardVisible": true,
      "isEditable": false,
      "isSaveVisible": true,
      "isVisible": true,
      "label": "ch4_mass",
      "notation": "standard",
      "originalId": "ch4_mass",
      "sticky": "",
      "textColor": "",
      "textSize": "0.875rem",
      "thousandSeparator": true,
      "validation": {},
      "verticalAlignment": "CENTER",
      "width": 150
    },
    "co2_energy": {
      "alias": "co2_energy",
      "allowCellWrapping": false,
      "allowSameOptionsInNewRow": true,
      "cellBackground": "",
      "columnType": "number",
      "computedValue": "{{Table1.processedTableData.map((currentRow, currentIndex) => ( currentRow[\"co2_energy\"]))}}",
      "currencyCode": "USD",
      "decimals": 0,
      "enableFilter": true,
      "enableSort": true,
      "fontStyle": "",
      "horizontalAlignment": "LEFT",
      "id": "co2_energy",
      "index": 3,
      "isCellEditable": false,
      "isCellVisible": true,
      "isDerived": false,
      "isDisabled": false,
      "isDiscardVisible": true,
      "isEditable": false,
      "isSaveVisible": true,
      "isVisible": true,
      "label": "co2_energy",
      "notation": "standard",
      "originalId": "co2_energy",
      "sticky": "",
      "textColor": "",
      "textSize": "0.875rem",
      "thousandSeparator": true,
      "validation": {},
      "verticalAlignment": "CENTER",
      "width": 150
    },
    "co2_mass": {
      "alias": "co2_mass",
      "allowCellWrapping": false,
      "allowSameOptionsInNewRow": true,
      "cellBackground": "",
      "columnType": "number",
      "computedValue": "{{Table1.processedTableData.map((currentRow, currentIndex) => ( currentRow[\"co2_mass\"]))}}",
      "currencyCode": "USD",
      "decimals": 0,
      "enableFilter": true,
      "enableSort": true,
      "fontStyle": "",
      "horizontalAlignment": "LEFT",
      "id": "co2_mass",
      "index": 8,
      "isCellEditable": false,
      "isCellVisible": true,
      "isDerived": false,
      "isDisabled": false,
      "isDiscardVisible": true,
      "isEditable": false,
      "isSaveVisible": true,
      "isVisible": true,
      "label": "co2_mass",
      "notation": "standard",
      "originalId": "co2_mass",
      "sticky": "",
      "textColor": "",
      "textSize": "0.875rem",
      "thousandSeparator": true,
      "validation": {},
      "verticalAlignment": "CENTER",
      "width": 150
    },
    "co2e_energy": {
      "alias": "co2e_energy",
      "allowCellWrapping": false,
      "allowSameOptionsInNewRow": true,
      "cellBackground": "",
      "columnType": "number",
      "computedValue": "{{Table1.processedTableData.map((currentRow, currentIndex) => ( currentRow[\"co2e_energy\"]))}}",
      "currencyCode": "USD",
      "decimals": 0,
      "enableFilter": true,
      "enableSort": true,
      "fontStyle": "",
      "horizontalAlignment": "LEFT",
      "id": "co2e_energy",
      "index": 6,
      "isCellEditable": false,
      "isCellVisible": true,
      "isDerived": false,
      "isDisabled": false,
      "isDiscardVisible": true,
      "isEditable": false,
      "isSaveVisible": true,
      "isVisible": true,
      "label": "co2e_energy",
      "notation": "standard",
      "originalId": "co2e_energy",
      "sticky": "",
      "textColor": "",
      "textSize": "0.875rem",
      "thousandSeparator": true,
      "validation": {},
      "verticalAlignment": "CENTER",
      "width": 150
    },
    "co2e_mass": {
      "alias": "co2e_mass",
      "allowCellWrapping": false,
      "allowSameOptionsInNewRow": true,
      "cellBackground": "",
      "columnType": "number",
      "computedValue": "{{Table1.processedTableData.map((currentRow, currentIndex) => ( currentRow[\"co2e_mass\"]))}}",
      "currencyCode": "USD",
      "decimals": 0,
      "enableFilter": true,
      "enableSort": true,
      "fontStyle": "",
      "horizontalAlignment": "LEFT",
      "id": "co2e_mass",
      "index": 11,
      "isCellEditable": false,
      "isCellVisible": true,
      "isDerived": false,
      "isDisabled": false,
      "isDiscardVisible": true,
      "isEditable": false,
      "isSaveVisible": true,
      "isVisible": true,
      "label": "co2e_mass",
      "notation": "standard",
      "originalId": "co2e_mass",
      "sticky": "",
      "textColor": "",
      "textSize": "0.875rem",
      "thousandSeparator": true,
      "validation": {},
      "verticalAlignment": "CENTER",
      "width": 150
    },
    "created_by": {
      "alias": "created_by",
      "allowCellWrapping": false,
      "allowSameOptionsInNewRow": true,
      "cellBackground": "",
      "columnType": "text",
      "computedValue": "{{Table1.processedTableData.map((currentRow, currentIndex) => ( currentRow[\"created_by\"]))}}",
      "enableFilter": true,
      "enableSort": true,
      "fontStyle": "",
      "horizontalAlignment": "LEFT",
      "id": "created_by",
      "index": 9,
      "isCellEditable": false,
      "isCellVisible": true,
      "isDerived": false,
      "isDisabled": false,
      "isDiscardVisible": true,
      "isEditable": false,
      "isSaveVisible": true,
      "isVisible": true,
      "label": "created_by",
      "originalId": "created_by",
      "sticky": "",
      "textColor": "",
      "textSize": "0.875rem",
      "validation": {},
      "verticalAlignment": "CENTER",
      "width": 150
    },
    "gwp": {
      "alias": "gwp",
      "allowCellWrapping": false,
      "allowSameOptionsInNewRow": true,
      "cellBackground": "",
      "columnType": "text",
      "computedValue": "{{Table1.processedTableData.map((currentRow, currentIndex) => ( currentRow[\"gwp\"]))}}",
      "currencyCode": "USD",
      "decimals": 0,
      "enableFilter": true,
      "enableSort": true,
      "fontStyle": "",
      "horizontalAlignment": "LEFT",
      "id": "gwp",
      "index": 12,
      "isCellEditable": false,
      "isCellVisible": true,
      "isDerived": false,
      "isDisabled": false,
      "isDiscardVisible": true,
      "isEditable": false,
      "isSaveVisible": true,
      "isVisible": true,
      "label": "gwp",
      "notation": "standard",
      "originalId": "gwp",
      "sticky": "",
      "textColor": "",
      "textSize": "0.875rem",
      "thousandSeparator": true,
      "validation": {},
      "verticalAlignment": "CENTER",
      "width": 150
    },
    "id": {
      "alias": "id",
      "allowCellWrapping": false,
      "allowSameOptionsInNewRow": true,
      "columnType": "number",
      "computedValue": "{{Table1.processedTableData.map((currentRow, currentIndex) => ( currentRow[\"id\"]))}}",
      "enableFilter": true,
      "enableSort": true,
      "horizontalAlignment": "LEFT",
      "id": "id",
      "index": 0,
      "isCellEditable": false,
      "isCellVisible": true,
      "isDerived": false,
      "isDisabled": false,
      "isDiscardVisible": true,
      "isEditable": false,
      "isSaveVisible": true,
      "isVisible": true,
      "label": "id",
      "originalId": "id",
      "sticky": "",
      "textSize": "0.875rem",
      "validation": {},
      "verticalAlignment": "CENTER",
      "width": 150
    },
    "n2o_energy": {
      "alias": "n2o_energy",
      "allowCellWrapping": false,
      "allowSameOptionsInNewRow": true,
      "cellBackground": "",
      "columnType": "number",
      "computedValue": "{{Table1.processedTableData.map((currentRow, currentIndex) => ( currentRow[\"n2o_energy\"]))}}",
      "currencyCode": "USD",
      "decimals": 0,
      "enableFilter": true,
      "enableSort": true,
      "fontStyle": "",
      "horizontalAlignment": "LEFT",
      "id": "n2o_energy",
      "index": 5,
      "isCellEditable": false,
      "isCellVisible": true,
      "isDerived": false,
      "isDisabled": false,
      "isDiscardVisible": true,
      "isEditable": false,
      "isSaveVisible": true,
      "isVisible": true,
      "label": "n2o_energy",
      "notation": "standard",
      "originalId": "n2o_energy",
      "sticky": "",
      "textColor": "",
      "textSize": "0.875rem",
      "thousandSeparator": true,
      "validation": {},
      "verticalAlignment": "CENTER",
      "width": 150
    },
    "n2o_mass": {
      "alias": "n2o_mass",
      "allowCellWrapping": false,
      "allowSameOptionsInNewRow": true,
      "cellBackground": "",
      "columnType": "number",
      "computedValue": "{{Table1.processedTableData.map((currentRow, currentIndex) => ( currentRow[\"n2o_mass\"]))}}",
      "currencyCode": "USD",
      "decimals": 0,
      "enableFilter": true,
      "enableSort": true,
      "fontStyle": "",
      "horizontalAlignment": "LEFT",
      "id": "n2o_mass",
      "index": 10,
      "isCellEditable": false,
      "isCellVisible": true,
      "isDerived": false,
      "isDisabled": false,
      "isDiscardVisible": true,
      "isEditable": false,
      "isSaveVisible": true,
      "isVisible": true,
      "label": "n2o_mass",
      "notation": "standard",
      "originalId": "n2o_mass",
      "sticky": "",
      "textColor": "",
      "textSize": "0.875rem",
      "thousandSeparator": true,
      "validation": {},
      "verticalAlignment": "CENTER",
      "width": 150
    },
    "notes": {
      "alias": "notes",
      "allowCellWrapping": false,
      "allowSameOptionsInNewRow": true,
      "columnType": "text",
      "computedValue": "{{Table1.processedTableData.map((currentRow, currentIndex) => ( currentRow[\"notes\"]))}}",
      "enableFilter": true,
      "enableSort": true,
      "horizontalAlignment": "LEFT",
      "id": "notes",
      "index": 5,
      "isCellEditable": false,
      "isCellVisible": true,
      "isDerived": false,
      "isDisabled": false,
      "isDiscardVisible": true,
      "isEditable": false,
      "isSaveVisible": true,
      "isVisible": true,
      "label": "notes",
      "originalId": "notes",
      "sticky": "",
      "textSize": "0.875rem",
      "validation": {},
      "verticalAlignment": "CENTER",
      "width": 150
    },
    "reference": {
      "alias": "reference",
      "allowCellWrapping": false,
      "allowSameOptionsInNewRow": true,
      "cellBackground": "",
      "columnType": "text",
      "computedValue": "{{Table1.processedTableData.map((currentRow, currentIndex) => ( currentRow[\"reference\"]))}}",
      "enableFilter": true,
      "enableSort": true,
      "fontStyle": "",
      "horizontalAlignment": "LEFT",
      "id": "reference",
      "index": 10,
      "isCellEditable": false,
      "isCellVisible": true,
      "isDerived": false,
      "isDisabled": false,
      "isDiscardVisible": true,
      "isEditable": false,
      "isSaveVisible": true,
      "isVisible": true,
      "label": "reference",
      "originalId": "reference",
      "sticky": "",
      "textColor": "",
      "textSize": "0.875rem",
      "validation": {},
      "verticalAlignment": "CENTER",
      "width": 150
    },
    "role": {
      "alias": "role",
      "allowCellWrapping": false,
      "allowSameOptionsInNewRow": true,
      "cellBackground": "",
      "columnType": "text",
      "computedValue": "{{Table1.processedTableData.map((currentRow, currentIndex) => ( currentRow[\"role\"]))}}",
      "enableFilter": true,
      "enableSort": true,
      "fontStyle": "",
      "horizontalAlignment": "LEFT",
      "id": "role",
      "index": 11,
      "isCellEditable": false,
      "isCellVisible": true,
      "isDerived": false,
      "isDisabled": false,
      "isDiscardVisible": true,
      "isEditable": false,
      "isSaveVisible": true,
      "isVisible": true,
      "label": "role",
      "originalId": "role",
      "sticky": "",
      "textColor": "",
      "textSize": "0.875rem",
      "validation": {},
      "verticalAlignment": "CENTER",
      "width": 150
    },
    "source": {
      "alias": "source",
      "allowCellWrapping": true,
      "allowSameOptionsInNewRow": true,
      "columnType": "text",
      "computedValue": "{{Table1.processedTableData.map((currentRow, currentIndex) => ( currentRow[\"source\"]))}}",
      "enableFilter": true,
      "enableSort": true,
      "horizontalAlignment": "LEFT",
      "id": "source",
      "index": 1,
      "isCellEditable": false,
      "isCellVisible": true,
      "isDerived": false,
      "isDisabled": false,
      "isDiscardVisible": true,
      "isEditable": false,
      "isSaveVisible": true,
      "isVisible": true,
      "label": "source",
      "originalId": "source",
      "sticky": "",
      "textSize": "0.875rem",
      "validation": {},
      "verticalAlignment": "CENTER",
      "width": 150
    },
    "unit_energy": {
      "alias": "unit_energy",
      "allowCellWrapping": false,
      "allowSameOptionsInNewRow": true,
      "cellBackground": "",
      "columnType": "text",
      "computedValue": "{{Table1.processedTableData.map((currentRow, currentIndex) => ( currentRow[\"unit_energy\"]))}}",
      "currencyCode": "USD",
      "decimals": 0,
      "enableFilter": true,
      "enableSort": true,
      "fontStyle": "",
      "horizontalAlignment": "LEFT",
      "id": "unit_energy",
      "index": 2,
      "isCellEditable": false,
      "isCellVisible": true,
      "isDerived": false,
      "isDisabled": false,
      "isDiscardVisible": true,
      "isEditable": false,
      "isSaveVisible": true,
      "isVisible": true,
      "label": "unit_energy",
      "notation": "standard",
      "originalId": "unit_energy",
      "sticky": "",
      "textColor": "",
      "textSize": "0.875rem",
      "thousandSeparator": true,
      "validation": {},
      "verticalAlignment": "CENTER",
      "width": 150
    },
    "unit_mass": {
      "alias": "unit_mass",
      "allowCellWrapping": false,
      "allowSameOptionsInNewRow": true,
      "cellBackground": "",
      "columnType": "text",
      "computedValue": "{{Table1.processedTableData.map((currentRow, currentIndex) => ( currentRow[\"unit_mass\"]))}}",
      "currencyCode": "USD",
      "decimals": 0,
      "enableFilter": true,
      "enableSort": true,
      "fontStyle": "",
      "horizontalAlignment": "LEFT",
      "id": "unit_mass",
      "index": 7,
      "isCellEditable": false,
      "isCellVisible": true,
      "isDerived": false,
      "isDisabled": false,
      "isDiscardVisible": true,
      "isEditable": false,
      "isSaveVisible": true,
      "isVisible": true,
      "label": "unit_mass",
      "notation": "standard",
      "originalId": "unit_mass",
      "sticky": "",
      "textColor": "",
      "textSize": "0.875rem",
      "thousandSeparator": true,
      "validation": {},
      "verticalAlignment": "CENTER",
      "width": 150
    },
    "year": {
      "alias": "year",
      "allowCellWrapping": false,
      "allowSameOptionsInNewRow": true,
      "cellBackground": "",
      "columnType": "number",
      "computedValue": "{{Table1.processedTableData.map((currentRow, currentIndex) => ( currentRow[\"year\"]))}}",
      "enableFilter": true,
      "enableSort": true,
      "fontStyle": "",
      "horizontalAlignment": "LEFT",
      "id": "year",
      "index": 7,
      "isCellEditable": false,
      "isCellVisible": true,
      "isDerived": false,
      "isDisabled": false,
      "isDiscardVisible": true,
      "isEditable": false,
      "isSaveVisible": true,
      "isVisible": true,
      "label": "year",
      "originalId": "year",
      "sticky": "",
      "textColor": "",
      "textSize": "0.875rem",
      "validation": {},
      "verticalAlignment": "CENTER",
      "width": 150
    }
  },
  "renderMode": "CANVAS",
  "responsiveBehavior": "fill",
  "rightColumn": 64,
  "searchKey": "",
  "serverSidePaginationEnabled": false,
  "showInlineEditingOptionDropdown": true,
  "tableData": "{{display_scope1sc.data}}",
  "tags": [
    "Suggested",
    "Display"
  ],
  "textSize": "0.875rem",
  "topRow": 4,
  "totalRecordsCount": "",
  "type": "TABLE_WIDGET_V2",
  "version": 2,
  "verticalAlignment": "CENTER",
  "widgetId": "1mra7hkm0f",
  "widgetName": "Table1"
}